flup/__init__.py
flup/client/__init__.py
flup/client/fcgi_app.py
flup/client/scgi_app.py
flup/server/__init__.py
flup/server/ajp.py
flup/server/ajp_base.py
flup/server/ajp_fork.py
flup/server/cgi.py
flup/server/fcgi.py
flup/server/fcgi_base.py
flup/server/fcgi_fork.py
flup/server/fcgi_single.py
flup/server/paste_factory.py
flup/server/preforkserver.py
flup/server/scgi.py
flup/server/scgi_base.py
flup/server/scgi_fork.py
flup/server/singleserver.py
flup/server/threadedserver.py
flup/server/threadpool.py
flup_py3-1.0.3.dist-info/DESCRIPTION.rst
flup_py3-1.0.3.dist-info/METADATA
flup_py3-1.0.3.dist-info/RECORD
flup_py3-1.0.3.dist-info/WHEEL
flup_py3-1.0.3.dist-info/entry_points.txt
flup_py3-1.0.3.dist-info/metadata.json
flup_py3-1.0.3.dist-info/top_level.txt
flup_py3-1.0.3.dist-info/zip-safe
